README.md
setup.cfg
setup.py
topsis_bhanu/__init__.py
topsis_bhanu/topsis_bhanu.py
topsis_bhanu/topsis_code.py
topsis_bhanu.egg-info/PKG-INFO
topsis_bhanu.egg-info/SOURCES.txt
topsis_bhanu.egg-info/dependency_links.txt
topsis_bhanu.egg-info/top_level.txt