Metadata-Version: 2.1
Name: topsis-bhanu
Version: 0.0.3
Summary: Implementation of topsis over a csv datafile using the distance calculation and comparison approach
Home-page: https://github.com/eternaldemon/topsis_bhanu
Author: Bhanu/eternal_demon
Author-email: aggarwal.bhanu02@gmail.com
License: UNKNOWN
Download-URL: https://github.com/eternaldemon/topsis_bhanu/archive/0.0.3.tar.gz
Platform: UNKNOWN
Classifier: Programming Language :: Python :: 3
Classifier: License :: OSI Approved :: MIT License
Classifier: Operating System :: OS Independent
Requires-Python: >=3.6
